leanclient/__init__.py
leanclient/base_client.py
leanclient/client.py
leanclient/file_manager.py
leanclient/info_tree.py
leanclient/pool.py
leanclient/single_file_client.py
leanclient/utils.py
leanclient-0.8.0.dist-info/METADATA
leanclient-0.8.0.dist-info/WHEEL
leanclient-0.8.0.dist-info/licenses/LICENSE
leanclient-0.8.0.dist-info/RECORD
