Metadata-Version: 2.4
Name: leanclient
Version: 0.8.0
Summary: Interact with the Lean theorem prover language server
Project-URL: Homepage, https://github.com/oOo0oOo/leanclient
Project-URL: Repository, https://github.com/oOo0oOo/leanclient
Project-URL: Documentation, https://leanclient.readthedocs.io
Author-email: Oliver Dressler <hey@oli.show>
License: MIT
License-File: LICENSE
Requires-Python: >=3.10
Requires-Dist: orjson>=3.11.1
Requires-Dist: tqdm>=4.67.1
Provides-Extra: dev
Requires-Dist: gprof2dot>=2024.6.6; extra == 'dev'
Requires-Dist: ipykernel>=6.29.5; extra == 'dev'
Requires-Dist: ruff>=0.8.0; extra == 'dev'
Requires-Dist: sphinx-rtd-theme>=3.0.2; extra == 'dev'
Requires-Dist: sphinx>=8.1.3; extra == 'dev'
Provides-Extra: test
Requires-Dist: psutil>=5.9; extra == 'test'
Requires-Dist: pytest-benchmark>=4.0; extra == 'test'
Requires-Dist: pytest-cov>=4.1; extra == 'test'
Requires-Dist: pytest-sugar>=1.0; extra == 'test'
Requires-Dist: pytest-timeout>=2.2; extra == 'test'
Requires-Dist: pytest-xdist>=3.5; extra == 'test'
Requires-Dist: pytest>=8.0; extra == 'test'
